nzconf/__init__.py
nzconf/__version__.py
nzconf/file.py
nzconf/formats/__init__.py
nzconf/formats/ini.py
nzconf/formats/js.py
nzconf/formats/yml.py
nzconf-1b0.post7.data/data/requirements.txt
nzconf-1b0.post7.dist-info/METADATA
nzconf-1b0.post7.dist-info/WHEEL
nzconf-1b0.post7.dist-info/entry_points.txt
nzconf-1b0.post7.dist-info/top_level.txt
nzconf-1b0.post7.dist-info/RECORD
