Metadata-Version: 2.1
Name: nzconf
Version: 1b0.post7
Summary: Configuration files manager
Home-page: UNKNOWN
Author: Clement
Author-email: neze+pypi@melix.org
License: UNKNOWN
Platform: UNKNOWN
Classifier: Programming Language :: Python :: 3
Classifier: Development Status :: 4 - Beta
Requires-Dist: PyYAML (>=3.13)
Requires-Dist: pathlib2 (>=2.3.3)
